PyEnhance/Banners.py
PyEnhance/Counter.py
PyEnhance/Loading.py
PyEnhance/Stamps.py
PyEnhance/TextSets.py
PyEnhance/Timer.py
PyEnhance/WebTools.py
PyEnhance/__init__.py
PyEnhance-0.1.3.1.dist-info/METADATA
PyEnhance-0.1.3.1.dist-info/WHEEL
PyEnhance-0.1.3.1.dist-info/top_level.txt
PyEnhance-0.1.3.1.dist-info/RECORD
