Metadata-Version: 2.1
Name: PyEnhance
Version: 0.1.3.1
Summary: A collection of essential scripts for any python project.
Home-page: https://github.com/BirdsAreFlyingCameras/PyEnhance
Author: Not A Bird
Requires-Dist: colorama (==0.4.6)
Requires-Dist: cursor (==1.3.5)
Requires-Dist: Requests (==2.31.0)
